ocha_stratus/__init__.py
ocha_stratus/_version.py
ocha_stratus/azure_blob.py
ocha_stratus/azure_database.py
ocha_stratus/cogs.py
ocha_stratus/datasources/__init__.py
ocha_stratus/datasources/cerf.py
ocha_stratus/datasources/codab.py
ocha_stratus/datasources/emdat.py
ocha_stratus-0.1.7.dist-info/METADATA
ocha_stratus-0.1.7.dist-info/WHEEL
ocha_stratus-0.1.7.dist-info/licenses/LICENSE
ocha_stratus-0.1.7.dist-info/RECORD
