Metadata-Version: 2.4
Name: ocha-stratus
Version: 0.1.7
Summary: Utilities for accessing data from Azure cloud storage
Project-URL: Homepage, https://github.com/OCHA-DAP/ocha-stratus
Project-URL: Repository, https://github.com/OCHA-DAP/ocha-stratus.git
Project-URL: Bug Tracker, https://github.com/OCHA-DAP/ocha-stratus/issues
Author-email: Hannah Ker <hannah.ker@un.org>, Tristan Downing <tristan.downing@un.org>
License: MIT
License-File: LICENSE
Classifier: Development Status :: 3 - Alpha
Classifier: Intended Audience :: Developers
Classifier: License :: OSI Approved :: MIT License
Classifier: Programming Language :: Python :: 3
Classifier: Programming Language :: Python :: 3.10
Classifier: Programming Language :: Python :: 3.11
Classifier: Programming Language :: Python :: 3.12
Classifier: Programming Language :: Python :: 3.13
Requires-Python: >=3.10
Requires-Dist: aiohttp>=3.12.15
Requires-Dist: azure-storage-blob>=12.20.0
Requires-Dist: dask>2024.8.0
Requires-Dist: duckdb>=1.4.0
Requires-Dist: fsspec>=2025.5.1
Requires-Dist: geopandas>=1.0.1
Requires-Dist: jinja2>=3.1.6
Requires-Dist: pandas>=2.2.2
Requires-Dist: psycopg2-binary>=2.9.10
Requires-Dist: pyarrow>=20.0.0
Requires-Dist: rioxarray>=0.17.0
Requires-Dist: sqlalchemy>=2.0.36
Requires-Dist: tqdm>=4.67.1
Requires-Dist: xarray>=2024.7.0
Provides-Extra: dev
Requires-Dist: pre-commit>=3.8.0; extra == 'dev'
Requires-Dist: pytest; extra == 'dev'
Requires-Dist: python-dotenv>=1.0.1; extra == 'dev'
Requires-Dist: ruff>=0.9.6; extra == 'dev'
Provides-Extra: docs
Requires-Dist: furo>=2024.1.29; extra == 'docs'
Requires-Dist: myst-parser>=2.0.0; extra == 'docs'
Requires-Dist: sphinx-copybutton>=0.5.0; extra == 'docs'
Requires-Dist: sphinx>=7.1.0; extra == 'docs'
